ckanext_saml2auth-1.3.0-py3.8-nspkg.pth
ckanext/saml2auth/__init__.py
ckanext/saml2auth/cache.py
ckanext/saml2auth/client.py
ckanext/saml2auth/helpers.py
ckanext/saml2auth/interfaces.py
ckanext/saml2auth/plugin.py
ckanext/saml2auth/spconfig.py
ckanext/saml2auth/templates/header.html
ckanext/saml2auth/templates/saml2auth/idp_logout.html
ckanext/saml2auth/templates/user/snippets/login_form.html
ckanext/saml2auth/tests/__init__.py
ckanext/saml2auth/tests/test_blueprint.py
ckanext/saml2auth/tests/test_blueprint_get_request.py
ckanext/saml2auth/tests/test_client.py
ckanext/saml2auth/tests/test_helpers.py
ckanext/saml2auth/tests/test_interface.py
ckanext/saml2auth/tests/test_spconfig.py
ckanext/saml2auth/views/__init__.py
ckanext/saml2auth/views/saml2auth.py
ckanext_saml2auth-1.3.0.dist-info/LICENSE
ckanext_saml2auth-1.3.0.dist-info/METADATA
ckanext_saml2auth-1.3.0.dist-info/NOTICE
ckanext_saml2auth-1.3.0.dist-info/WHEEL
ckanext_saml2auth-1.3.0.dist-info/entry_points.txt
ckanext_saml2auth-1.3.0.dist-info/namespace_packages.txt
ckanext_saml2auth-1.3.0.dist-info/top_level.txt
ckanext_saml2auth-1.3.0.dist-info/RECORD
