Metadata-Version: 2.1
Name: ckanext-saml2auth
Version: 1.3.0
Summary: An extension to enable Single Sign On(SSO) for CKAN data portals via SAML2 Authentication.
Home-page: https://github.com/keitaroinc/ckanext-saml2auth
Author: Keitaro Inc
Author-email: info@keitaro.com
License: AGPL
Keywords: CKAN ckanext saml2 sso
Classifier: Development Status :: 5 - Production/Stable
Classifier: License :: OSI Approved :: GNU Affero General Public License v3 or later (AGPLv3+)
Classifier: Programming Language :: Python :: 3 :: Only
Classifier: Programming Language :: Python :: 3.6
Classifier: Programming Language :: Python :: 3.7
Classifier: Programming Language :: Python :: 3.8
License-File: LICENSE
License-File: NOTICE
Requires-Dist: pysaml2 (>=6.5.1)
